[{"id":"0469-6501","name":"regadenoson","form":"INJECTION, SOLUTION","route":"INTRAVENOUS"},{"id":"0781-1684","name":"cetirizine hydrochloride","form":"TABLET","route":"ORAL"},{"id":"65162-003","name":"cetirizine","form":"SOLUTION","route":"ORAL"},{"id":"41163-475","name":"cetirizine hcl","form":"SOLUTION","route":"ORAL"},{"id":"59779-176","name":"cetirizine hcl, pseudoephedrine hcl","form":"TABLET, EXTENDED RELEASE","route":"ORAL"},{"id":"70000-0163","name":"cetirizine hydrochloride and pseudoephedrine hydrochloride","form":"TABLET, FILM COATED, EXTENDED RELEASE","route":"ORAL"},{"id":"62011-0307","name":"cetirizine hydrochloride tablets","form":"TABLET, FILM COATED","route":"ORAL"},{"id":"21695-781","name":"colesevelam hydrochloride","form":"TABLET, FILM COATED","route":"ORAL"},{"id":"76140-105","name":"dextromethorphan hydrobromide, guaifenesin, and phenylephrine hydrochloride","form":"LIQUID","route":"ORAL"},{"id":"43378-126","name":"codeine phosphate, guaifenesin and pseudoephedrine hydrochloride","form":"SUSPENSION","route":"ORAL"},{"id":"49348-199","name":"dextromethorphan hbr, guaifenesin","form":"TABLET, EXTENDED RELEASE","route":"ORAL"},{"id":"41250-507","name":"guaifenesin","form":"SOLUTION","route":"ORAL"},{"id":"0113-0381","name":"acetaminophen, dextromethorphan hbr, guaifenesin, phenylephrine hcl","form":"TABLET, FILM COATED","route":"ORAL"},{"id":"41163-269","name":"acetaminophen, dextromethorphan hbr, guaifenesin, phenylephrine hcl, doxylamine succinate","form":"KIT","route":null},{"id":"37205-696","name":"dextromethorphan hbr, guaifenesin, phenylephrine hcl","form":"LIQUID","route":"ORAL"},{"id":"58238-229","name":"dextromethorphan hydrobromide, guaifenesin","form":"LIQUID","route":"ORAL"},{"id":"52083-617","name":"dextromethorphan hydrobromide, guaifenesin, phenylephrine hydrochloride","form":"TABLET","route":"ORAL"},{"id":"0031-8737","name":"dextromethorphan hydrobromide and guaifenesin","form":"SOLUTION","route":"ORAL"},{"id":"63187-960","name":"guaifenesin, pseudoephedrine hydrochloride","form":"TABLET, EXTENDED RELEASE","route":"ORAL"},{"id":"61715-011","name":"acetaminophen, guaifenesin, and phenylephrine hydrochloride","form":"TABLET, COATED","route":"ORAL"},{"id":"37000-811","name":"acetaminophen, dextromethorphan hydrobromide, guaifenesin, and phenylephrine hydrochloride","form":"TABLET","route":"ORAL"},{"id":"59741-116","name":"guaifenesin and dextromethorphan hydrobromide","form":"SOLUTION","route":"ORAL"},{"id":"49580-0382","name":"dextromethorphan hbr, guaifenesin, phenylephrine","form":"LIQUID","route":"ORAL"},{"id":"10956-761","name":"dextromethorphan hydrobromide \/  guaifenesin","form":"TABLET","route":"ORAL"},{"id":"70000-0285","name":"acetaminophen, guaifenesin, phenylephrine hcl","form":"TABLET, FILM COATED","route":"ORAL"},{"id":"37205-610","name":"dextromethorphan hydrobromide \/ guaifenesin","form":"LIQUID","route":"ORAL"},{"id":"71027-020","name":"rapid max maximum strength cool and clear - cold, severe congestion and cough","form":"LIQUID","route":"ORAL"},{"id":"55315-527","name":"acetaminophen, guaifenesin and phenylephrine hcl","form":"TABLET, FILM COATED","route":"ORAL"},{"id":"30142-315","name":"acetaminohpen, guaifenesin, phenylephrine hcl","form":"LIQUID","route":"ORAL"},{"id":"70000-0133","name":"dextromethorphan hbr, guaifenesin, phenylephrine hci","form":"LIQUID","route":"ORAL"},{"id":"47682-187","name":"acetaminophen, guaifenesin, phenylephrine hydrochloride","form":"TABLET","route":"ORAL"},{"id":"11822-6485","name":"dextromethorphan hbr, guaifenesin, phenylephrine hcl, acetaminophen, diphenhydramine hcl","form":"KIT","route":null},{"id":"63824-551","name":"acetaminophen, dextromethorphan hydrobromide, diphenhydramine hydrochloride, guaifenesin, and phenylephrine hydrochloride","form":"KIT","route":null},{"id":"68016-182","name":"guaifenesin and phenylephrine hcl","form":"TABLET","route":"ORAL"},{"id":"54859-502","name":"dextromethorphan, guiafenesin, pseudoephedrine hcl","form":"LIQUID","route":"ORAL"},{"id":"0363-5270","name":"aceetaminophen, guaifenesin and phenylephrine hcl","form":"TABLET, FILM COATED","route":"ORAL"},{"id":"63102-102","name":"dextromethorphan hbr,guaifenesin,pseudoephedrine hcl","form":"SOLUTION","route":"ORAL"},{"id":"66007-204","name":"guaifenesin and dextromethorphan","form":"GRANULE","route":"ORAL"},{"id":"53145-333","name":"dextromethorphan, guiafenesin, phenylephrine","form":"SOLUTION","route":"ORAL"},{"id":"62583-003","name":"dextromethorphan hbr guaifenesin phenylephrine hcl","form":"SYRUP","route":"ORAL"},{"id":"47682-159","name":"acetaminophen, dextromethorphan hydrobromide, guaifenesin, phenylephrine hydrochloride","form":"TABLET","route":"ORAL"},{"id":"0121-0775","name":"guaifenesin and codeine phosphate","form":"SOLUTION","route":"ORAL"},{"id":"35573-006","name":"codeine phosphate and guaifenesin","form":"LIQUID","route":"ORAL"},{"id":"55315-503","name":"acetaminophen, phenylephrine hcl, dextromethorphan hbr and guaifenesin","form":"TABLET, FILM COATED","route":"ORAL"},{"id":"0002-7511","name":"insulin lispro","form":"INJECTION, SUSPENSION","route":"SUBCUTANEOUS"},{"id":"0615-7569","name":"fluvoxamine maleate","form":"TABLET, FILM COATED","route":"ORAL"},{"id":"50090-1127","name":"nebivolol hydrochloride","form":"TABLET","route":"ORAL"},{"id":"0023-5874","name":"nebivolol hydrochloride and valsartan","form":"TABLET, FILM COATED","route":"ORAL"},{"id":"43975-248","name":"nebivolol","form":"TABLET","route":"ORAL"},{"id":"66116-603","name":"prednisolone","form":"SOLUTION","route":"ORAL"},{"id":"68083-176","name":"oxaliplatin","form":"INJECTION, SOLUTION","route":"INTRAVENOUS"},{"id":"0409-4699","name":"propofol","form":"INJECTION, EMULSION","route":"INTRAVENOUS"},{"id":"49836-023","name":"propofol ,isopropyl alcohol","form":"KIT","route":null},{"id":"49836-024","name":"propofol, sterile isopropyl alcohol","form":"KIT","route":null},{"id":"52584-269","name":"diprivan","form":"INJECTION, EMULSION","route":"INTRAVENOUS"},{"id":"49836-025","name":"propofol, isopropyl alcohol","form":"KIT","route":null},{"id":"54868-5701","name":"methadone hydrochloride","form":"TABLET","route":"ORAL"},{"id":"50881-005","name":"ruxolitinib","form":"TABLET","route":"ORAL"},{"id":"17478-102","name":"tropicamide","form":"SOLUTION\/ DROPS","route":"OPHTHALMIC"},{"id":"17478-704","name":"hydroxyamphetamine hydrobromide, tropicamide","form":"SOLUTION","route":"OPHTHALMIC"},{"id":"60429-989","name":"clozapine","form":"TABLET","route":"ORAL"},{"id":"0378-9671","name":"ipratropium bromide and albuterol sulfate","form":"SOLUTION","route":"RESPIRATORY (INHALATION)"},{"id":"16590-339","name":"albuterol sulfate","form":"AEROSOL, METERED","route":"RESPIRATORY (INHALATION)"},{"id":"21695-198","name":"albuterol","form":"AEROSOL, METERED","route":"ORAL"},{"id":"0597-0024","name":"ipratropium bromide and albuterol","form":"SPRAY, METERED","route":"RESPIRATORY (INHALATION)"},{"id":"70518-0476","name":"allopurinol","form":"TABLET","route":"ORAL"},{"id":"70785-022","name":"lesinurad and allopurinol","form":"TABLET, FILM COATED","route":"ORAL"},{"id":"0143-9533","name":"allopurinol sodium","form":"INJECTION, POWDER, LYOPHILIZED, FOR SOLUTION","route":"INTRAVENOUS"},{"id":"61919-051","name":"cephalexin","form":"CAPSULE","route":"ORAL"},{"id":"69299-202","name":"betamethasone","form":"OINTMENT","route":"TOPICAL"},{"id":"54868-4354","name":"pioglitazone hydrochloride","form":"TABLET","route":"ORAL"},{"id":"71335-0088","name":"pioglitazone","form":"TABLET","route":"ORAL"},{"id":"63187-746","name":"pioglitazonehydrochloride","form":"TABLET","route":"ORAL"},{"id":"70882-105","name":"pioglitazone and metformin","form":"TABLET, FILM COATED","route":"ORAL"},{"id":"42291-512","name":"pioglitazone and metformin hydrochloride","form":"TABLET, FILM COATED","route":"ORAL"},{"id":"64764-254","name":"alogliptin and pioglitazone","form":"TABLET, FILM COATED","route":"ORAL"},{"id":"65862-525","name":"pioglitazone hydrochloride and metformin hydrochloride","form":"TABLET, FILM COATED","route":"ORAL"},{"id":"13668-281","name":"pioglitazone hcl and metformin hcl","form":"TABLET","route":"ORAL"},{"id":"33342-176","name":"pioglitazole and metformin hydrochloride","form":"TABLET","route":"ORAL"},{"id":"0781-5635","name":"pioglitazone hydrochloride and glimepiride","form":"TABLET","route":"ORAL"},{"id":"45802-304","name":"alogliptin benzoate and pioglitazone hydrochloride","form":"TABLET, FILM COATED","route":"ORAL"},{"id":"66993-822","name":"pioglitazone and glimepiride","form":"TABLET","route":"ORAL"},{"id":"59779-520","name":"loperamide hydrochloride","form":"CAPSULE, LIQUID FILLED","route":"ORAL"},{"id":"50844-753","name":"loperamide hcl","form":"TABLET","route":"ORAL"},{"id":"0407-2707","name":"human albumin microspheres and perflutren","form":"INJECTION, SOLUTION","route":"INTRAVENOUS"},{"id":"11994-011","name":"perflutren","form":"INJECTION, SUSPENSION","route":"INTRAVENOUS"},{"id":"53964-001","name":"thiotepa","form":"INJECTION, POWDER, FOR SOLUTION","route":"INTRAVENOUS"},{"id":"57894-199","name":"abiraterone acetate","form":"TABLET, FILM COATED","route":"ORAL"},{"id":"0046-0872","name":"conjugated estrogens","form":"CREAM","route":"VAGINAL"},{"id":"68258-5978","name":"conjugated estrogens and medroxyprogesterone acetate","form":"TABLET, SUGAR COATED","route":"ORAL"},{"id":"63539-112","name":"conjugated estrogens\/bazedoxifene","form":"TABLET, FILM COATED","route":"ORAL"},{"id":"69189-1105","name":"estrogens, conjugated","form":"TABLET, FILM COATED","route":"ORAL"},{"id":"53746-077","name":"esterified estrogens and methyltestosterone","form":"TABLET","route":"ORAL"},{"id":"69189-1201","name":"elvitegravir, cobicistat, emtricitabine, and tenofovir disoproxil fumarate","form":"TABLET, FILM COATED","route":"ORAL"},{"id":"50090-2279","name":"elvitegravir, cobicistat, emtricitabine, and tenofovir alafenamide","form":"TABLET","route":"ORAL"},{"id":"42291-587","name":"metaxalone","form":"TABLET","route":"ORAL"},{"id":"61919-262","name":"metaxalone tablet","form":"TABLET","route":"ORAL"},{"id":"64406-016","name":"peginterferon beta-1a","form":"KIT","route":null},{"id":"52533-101","name":"amiodarone hcl","form":"INJECTION, SOLUTION","route":"INTRAVENOUS"},{"id":"55154-5492","name":"amiodarone hydrochloride","form":"TABLET","route":"ORAL"},{"id":"42254-008","name":"methimazole","form":"TABLET","route":"ORAL"},{"id":"52652-4001","name":"enalapril maleate","form":"SOLUTION","route":"ORAL"},{"id":"0378-0723","name":"enalapril maleate and hydrochlorothiazide","form":"TABLET","route":"ORAL"},{"id":"66215-602","name":"selexipag","form":"TABLET, COATED","route":"ORAL"},{"id":"42291-153","name":"azelastine hydrochloride","form":"SPRAY, METERED","route":"NASAL"},{"id":"67877-477","name":"azelastine","form":"SPRAY, METERED","route":"NASAL"},{"id":"0037-0245","name":"azelastine hydrochloride and fluticasone propionate","form":"SPRAY, METERED","route":"NASAL"},{"id":"45802-026","name":"azelastine hcl","form":"SPRAY","route":"NASAL"},{"id":"54868-5969","name":"darunavir","form":"TABLET, FILM COATED","route":"ORAL"},{"id":"50090-1723","name":"darunavir ethanolate and cobicistat","form":"TABLET, FILM COATED","route":"ORAL"},{"id":"53808-0672","name":"darunavir ethanolate","form":"TABLET, FILM COATED","route":"ORAL"},{"id":"0703-1985","name":"epoprostenol sodium","form":"INJECTION, POWDER, FOR SOLUTION","route":"INTRAVENOUS"},{"id":"76112-402","name":"epoprostenol","form":"INJECTION, POWDER, LYOPHILIZED, FOR SOLUTION","route":"INTRAVENOUS"},{"id":"68094-757","name":"lithium","form":"SOLUTION","route":"ORAL"},{"id":"59572-402","name":"lenalidomide","form":"CAPSULE","route":"ORAL"},{"id":"61786-010","name":"lamotrigine","form":"TABLET","route":"ORAL"},{"id":"62332-095","name":"lamotrigine chewable dispersible","form":"TABLET, FOR SUSPENSION","route":"ORAL"},{"id":"52817-242","name":"lamotrigine extended release","form":"TABLET","route":"ORAL"},{"id":"55513-073","name":"cinacalcet hydrochloride","form":"TABLET, COATED","route":"ORAL"},{"id":"0078-0393","name":"basiliximab","form":"INJECTION, POWDER, FOR SOLUTION","route":"INTRAVENOUS"},{"id":"66658-234","name":"anakinra","form":"INJECTION, SOLUTION","route":"SUBCUTANEOUS"},{"id":"67296-0883","name":"metoclopramide hydrochloride","form":"TABLET","route":"ORAL"},{"id":"76237-299","name":"metoclopramide","form":"TABLET","route":"ORAL"},{"id":"76420-625","name":"magesium citrate, bisacodyl, petrolatum, polyethylene glycol 3350, metoclopramide","form":"KIT","route":"TOPICAL"},{"id":"63629-5292","name":"ticagrelor","form":"TABLET","route":"ORAL"},{"id":"55154-4227","name":"sirolimus","form":"TABLET, SUGAR COATED","route":"ORAL"},{"id":"0574-4160","name":"neomycin, polymyxin b sulfates, dexamethasone","form":"OINTMENT","route":"OPHTHALMIC"},{"id":"24208-830","name":"neomycin sulfate, polymyxin b sulfate and dexamethasone","form":"SUSPENSION\/ DROPS","route":"OPHTHALMIC"},{"id":"0054-8176","name":"dexamethasone","form":"TABLET","route":"ORAL"},{"id":"0065-8533","name":"ciprofloxacin and dexamethasone","form":"SUSPENSION\/ DROPS","route":"AURICULAR (OTIC)"},{"id":"63187-669","name":"neomycin sulfate, polymyxin b sulfate, and dexamethasone","form":"OINTMENT","route":"OPHTHALMIC"},{"id":"21695-203","name":"tobramycin and dexamethasone","form":"SUSPENSION","route":"OPHTHALMIC"},{"id":"16590-167","name":"neomycin, polymyxin b and dexamethasone","form":"SUSPENSION","route":"OPHTHALMIC"},{"id":"0054-3176","name":"dexamethasone intensol","form":"SOLUTION, CONCENTRATE","route":"ORAL"},{"id":"26637-941","name":"dexamethasone, neomycin sulfate, polymysin b sulfate","form":"OINTMENT","route":"OPHTHALMIC"},{"id":"68047-702","name":"dexamethasone 1.5 mg","form":"TABLET","route":"ORAL"},{"id":"61919-167","name":"neomycin polymyxin b sulfates and dexamethasone","form":"SUSPENSION\/ DROPS","route":"OPHTHALMIC"},{"id":"12753-930","name":"menthol","form":"OINTMENT","route":"TOPICAL"},{"id":"61314-631","name":"neomycin and polymyxin b sulfates and dexamethasone","form":"OINTMENT","route":"OPHTHALMIC"},{"id":"0065-0652","name":"tobramycin \/ dexamethasone","form":"SUSPENSION\/ DROPS","route":"OPHTHALMIC"},{"id":"67877-454","name":"itraconazole","form":"CAPSULE, COATED PELLETS","route":"ORAL"},{"id":"59746-282","name":"itraconazole capsules","form":"CAPSULE","route":"ORAL"},{"id":"61919-741","name":"levofloxacin","form":"TABLET","route":"ORAL"},{"id":"0615-8050","name":"lorazepam","form":"TABLET","route":"ORAL"},{"id":"54868-5384","name":"exenatide","form":"INJECTION","route":"SUBCUTANEOUS"},{"id":"50474-801","name":"rotigotine","form":"PATCH, EXTENDED RELEASE","route":"TRANSDERMAL"},{"id":"76519-1063","name":"atorvastatin calcium","form":"TABLET, FILM COATED","route":"ORAL"},{"id":"59762-6733","name":"amlodipine besylate and atorvastatin calcium","form":"TABLET, FILM COATED","route":"ORAL"},{"id":"60760-354","name":"atorvastatin calcium propylene glycol solvate","form":"TABLET, FILM COATED","route":"ORAL"},{"id":"59088-704","name":"diclofenac sodium, lidocaine, menthol","form":"KIT","route":null},{"id":"0496-0883","name":"lidocaine","form":"CREAM","route":"TOPICAL"},{"id":"54723-100","name":"lidocaine hydrochloride","form":"CREAM","route":"TOPICAL"},{"id":"70372-725","name":"lidocaine, menthol","form":"PATCH","route":"TOPICAL"},{"id":"69313-636","name":"lidoflex shoulder","form":"PATCH","route":"TOPICAL"},{"id":"56104-006","name":"burn relief spray","form":"AEROSOL, SPRAY","route":"TOPICAL"},{"id":"15455-9504","name":"lidocaine 2.5% and prilocaine 2.5%","form":"KIT","route":"TOPICAL"},{"id":"47682-300","name":"benzethonium chloride and lidocaine","form":"AEROSOL, SPRAY","route":"TOPICAL"},{"id":"69842-049","name":"lidocaine 4%","form":"LIQUID","route":"TOPICAL"},{"id":"52124-1166","name":"benzalkonium chloride, benzalkonium chloride, lidocaine, povidone-iodine, bacitracin zinc, neomycin sulfate, polymyxin b","form":"KIT","route":null},{"id":"50876-111","name":"topical lidocaine (4% w\/w)","form":"CREAM","route":"TOPICAL"},{"id":"52124-0111","name":"benzalkonium chloride, lidocaine, bacitracin zinc, neomycin sulfate, polymyxin b sulfate, water, benzocaine, alcohol, ibuprofen,  acetaminophen, aspirin","form":"KIT","route":null},{"id":"52584-483","name":"lidocaine hydrochloride and epinephrine","form":"INJECTION, SOLUTION","route":"INFILTRATION"},{"id":"69842-985","name":"lidocane and phenylephrine hcl","form":"CREAM","route":"TOPICAL"},{"id":"70877-5555","name":"lidocaine and prilocaine","form":"KIT","route":null},{"id":"52164-1102","name":"benzalkonium chloride, lidocaine, water, isopropyl alcohol, aspirin","form":"KIT","route":null},{"id":"69313-635","name":"lidoflex single pouch, knee","form":"PATCH","route":"TOPICAL"},{"id":"30142-906","name":"lidocaine menthol","form":"GEL","route":"TOPICAL"},{"id":"11673-564","name":"benzalkonium chloride, lidocaine","form":"SPRAY","route":"TOPICAL"},{"id":"69903-002","name":"lidocaine and benzethonium chloride cream","form":"CREAM","route":"TOPICAL"},{"id":"49836-007","name":"triamcinolone acetonide, bupivacaine hcl, lidocaine hcl, sodium chloride, povidone iodine, isopropyl alcohol","form":"KIT","route":null},{"id":"71301-003","name":"lidocaine hcl and menthol","form":"CREAM","route":"TOPICAL"},{"id":"69621-822","name":"lidocaine, isopropyl alcohol","form":"KIT","route":null},{"id":"0362-9010","name":"lidocaine hydrochloride and epinephrine bitartrate","form":"INJECTION, SOLUTION","route":"SUBCUTANEOUS"},{"id":"55154-6964","name":"lidocaine hydrochloride anhydrous","form":"INJECTION, SOLUTION","route":"INFILTRATION"},{"id":"52124-1154","name":"benzalkonium chloride, benzalkonium chloride, lidocaine, bacitracin zinc,neomycin sulfate,polymyxin b sulfate, povidone-iodine, water, alcohol, aspirin, ibuprofen, acetaminophen, benzocaine, alcohol","form":"KIT","route":null},{"id":"63135-563","name":"lidocaine 5%","form":"GEL","route":"TOPICAL"},{"id":"59779-230","name":"lidocaine  0.50%","form":"SPRAY","route":"TOPICAL"},{"id":"49430-053","name":"lidocaine, allantoin, petrolatum","form":"PATCH","route":"TOPICAL"},{"id":"76074-163","name":"capsaicin, lidocaine, menthol, and methyl salicylate","form":"PATCH","route":"TOPICAL"},{"id":"50436-9995","name":"methyl salicylate, capsaicin, menthol and lidocaine hydrochloride","form":"LOTION","route":"TOPICAL"},{"id":"0395-6110","name":"lidocaine-prilocaine-cream base","form":"CREAM","route":"TOPICAL"},{"id":"59088-705","name":"lidocaine and prilocaine, lidocaine hydrochloride","form":"KIT","route":null},{"id":"71248-002","name":"anodyne ile","form":"KIT","route":null},{"id":"69103-2400","name":"bacitracin zinc, neomycin sulfate, polymyxin b sulfate, lidocaine","form":"OINTMENT","route":"TOPICAL"},{"id":"70365-001","name":"allantoin and lidocaine","form":"CREAM","route":"TOPICAL"},{"id":"69020-210","name":"lidocaine hydrochloride phenol","form":"CREAM","route":"TOPICAL"},{"id":"76168-099","name":"lidocaine and menthol","form":"PATCH","route":"TOPICAL"},{"id":"52124-4016","name":"aspirin, acetaminophen, ibuprofen, bacitracin zinc, neomycin sulfate, polymyxin b, benzalkonium chloride, lidocaine, benzalkonium chloride","form":"KIT","route":null},{"id":"59779-256","name":"benzalkonium chloride and lidocaine hydrochloride","form":"LIQUID","route":"TOPICAL"},{"id":"52124-0107","name":"benzalkonium chloride, lidocaine, water, isotropyl alcohol, benzocaine, alcohol, aspirin","form":"KIT","route":null},{"id":"0069-0155","name":"cytarabine","form":"INJECTION","route":"INTRATHECAL"},{"id":"68727-745","name":"(daunorubicin and cytarabine) liposome","form":"INJECTION, POWDER, LYOPHILIZED, FOR SUSPENSION","route":"INTRAVENOUS"},{"id":"0078-0669","name":"ofatumumab","form":"INJECTION, SOLUTION","route":"INTRAVENOUS"},{"id":"55150-203","name":"vancomycin hydrochloride","form":"INJECTION, POWDER, LYOPHILIZED, FOR SOLUTION","route":"INTRAVENOUS"},{"id":"52533-071","name":"vancomycin hcl","form":"INJECTION, SOLUTION","route":"INTRAVENOUS"},{"id":"51991-940","name":"vancomycin","form":"INJECTION, SOLUTION","route":"INTRAVENOUS"},{"id":"23155-220","name":"vancomycin hydrocloride","form":"INJECTION, POWDER, LYOPHILIZED, FOR SOLUTION","route":"INTRAVENOUS"},{"id":"0406-8320","name":"morphine sulfate","form":"TABLET, EXTENDED RELEASE","route":"ORAL"},{"id":"60793-430","name":"morphine sulfate and naltrexone hydrochloride","form":"CAPSULE, EXTENDED RELEASE","route":"ORAL"},{"id":"70408-358","name":"morphine sulfate oral solution","form":"SOLUTION","route":"ORAL"},{"id":"62559-153","name":"morphine tincture","form":"SOLUTION","route":"ORAL"},{"id":"42799-217","name":"morphine","form":"TINCTURE","route":"ORAL"},{"id":"55319-876","name":"ranitidine","form":"TABLET, COATED","route":"ORAL"},{"id":"68094-316","name":"ranitidine hydrochloride","form":"SOLUTION","route":"ORAL"},{"id":"69168-375","name":"ranitidine hydrochloride tablets 150mg","form":"TABLET, COATED","route":"ORAL"},{"id":"59088-062","name":"diclofenac sodium delayed release tablets, ranitidine tablets, capsaicin cream","form":"KIT","route":null},{"id":"68405-033","name":"ranitidine hydrochloride, choline","form":"KIT","route":null},{"id":"37808-097","name":"triclosan","form":"LIQUID","route":"TOPICAL"},{"id":"51769-003","name":"undecylenic acid, triclosan","form":"CREAM","route":"CUTANEOUS"},{"id":"65601-759","name":"tricolsan","form":"SOAP","route":"TOPICAL"},{"id":"76162-103","name":"antibacterial","form":"LIQUID","route":"TOPICAL"},{"id":"65954-354","name":"sodium fluoride and triclosan","form":"GEL, DENTIFRICE","route":"DENTAL"},{"id":"41900-100","name":"advanced hand sanitizing gel","form":"GEL","route":"TOPICAL"},{"id":"49981-008","name":"anti-bacterial hand wash","form":"LIQUID","route":"TOPICAL"},{"id":"50865-640","name":"foaming antibacterial handwash","form":"SOLUTION","route":"TOPICAL"},{"id":"24673-249","name":"ethanol, triclosan","form":"SPRAY","route":"TOPICAL"},{"id":"55513-710","name":"denosumab","form":"INJECTION","route":"SUBCUTANEOUS"},{"id":"70518-0899","name":"metformin hydrochloride","form":"TABLET, EXTENDED RELEASE","route":"ORAL"},{"id":"23155-233","name":"glyburide-metformin hydrochloride","form":"TABLET","route":"ORAL"},{"id":"67877-561","name":"metformin hcl","form":"TABLET","route":"ORAL"},{"id":"45865-710","name":"glyburide and metformin hydrochloride","form":"TABLET, FILM COATED","route":"ORAL"},{"id":"0597-0146","name":"linagliptin and metformin hydrochloride","form":"TABLET, FILM COATED","route":"ORAL"},{"id":"0378-3133","name":"glipizide and metformin hydrochloride","form":"TABLET, FILM COATED","route":"ORAL"},{"id":"0310-6225","name":"dapagliflozin and metformin hydrochloride","form":"TABLET, FILM COATED, EXTENDED RELEASE","route":"ORAL"},{"id":"65162-175","name":"metformin","form":"TABLET","route":"ORAL"},{"id":"23155-115","name":"glipizide and metformin hcl","form":"TABLET, FILM COATED","route":"ORAL"},{"id":"51655-551","name":"metformin hydrochloride extended release","form":"TABLET","route":"ORAL"},{"id":"58411-299","name":"octinoxate and titanium dioxide","form":"LIQUID","route":"TOPICAL"},{"id":"13537-435","name":"octinoxate, octocrylene, oxybenzone, octisalate, titanium dioxide, and ensulizole","form":"CREAM","route":"TOPICAL"},{"id":"49967-000","name":"avobenzone, octocrylene, terephthalylidene dicamphor sulfonic acid and titanium dioxide","form":"LOTION","route":"TOPICAL"},{"id":"67345-0631","name":"titanium dioxide","form":"POWDER","route":"TOPICAL"},{"id":"61481-0045","name":"octinoxate, octisalate, oxybenzone, and titanium dioxide","form":"STICK","route":"TOPICAL"},{"id":"51790-505","name":"titanium dioxide and zinc oxide","form":"CREAM","route":"TOPICAL"},{"id":"71367-010","name":"titanium dioxide, octinoxate, zinc oxide, octisalate","form":"CREAM","route":"TOPICAL"},{"id":"51346-003","name":"titanium dioxide, octinoxate, octisalate","form":"CREAM","route":"TOPICAL"},{"id":"70803-410","name":"octinoxate, octocrylene, titanium dioxide, zinc oxide","form":"CREAM","route":"TOPICAL"},{"id":"60905-0046","name":"octinoxate, titanium dioxide","form":"EMULSION","route":"TOPICAL"},{"id":"10096-0260","name":"titanium dioxide, zinc oxide","form":"POWDER","route":"TOPICAL"},{"id":"76138-206","name":"octinoxate, octisalate, oxybenzone, titanium dioxide","form":"LOTION","route":"TOPICAL"},{"id":"45167-451","name":"octinoxate, titanium dioxide, enzacamene","form":"CREAM","route":"TOPICAL"},{"id":"71472-060","name":"titanium dioxide, octinoxate, octisalate, octocrylene, zinc oxide","form":"POWDER","route":"TOPICAL"},{"id":"52686-274","name":"octinoxate, octocrylene, titanium dioxide, and zinc oxide","form":"LOTION","route":"TOPICAL"},{"id":"69154-010","name":"titanium dioxide, octinoxate","form":"CREAM","route":"TOPICAL"},{"id":"69842-067","name":"octinoxate, octisalate, oxybenzone, titanium dioxide, zinc oxide","form":"LOTION","route":"TOPICAL"},{"id":"43526-114","name":"ethylhexyl methoxycinnamate, titanium dioxide, zinc oxide","form":"CREAM","route":"TOPICAL"},{"id":"47469-410","name":"titanium dioxide, octinoxate, octisalate, zinc oxide","form":"POWDER","route":"TOPICAL"},{"id":"49715-015","name":"titanium dioxide, zinc oxide, arbutin, adenosine","form":"CREAM","route":"TOPICAL"},{"id":"69106-090","name":"octinoxate, titanium dioxide, octisalate","form":"CREAM","route":"TOPICAL"},{"id":"51346-031","name":"octinoxate, titanium dioxide, zinc oxide","form":"CREAM","route":"TOPICAL"},{"id":"66184-533","name":"titanium dioxide and octinoxate","form":"LOTION","route":"TOPICAL"},{"id":"69017-201","name":"zinc oxide and titanium dioxide","form":"CREAM","route":"TOPICAL"},{"id":"71379-020","name":"octinoxate, octisalate, zinc oxide, titanium dioxide","form":"CREAM","route":"TOPICAL"},{"id":"51386-737","name":"octinoxate, octisalate, titanium dioxide","form":"STICK","route":"TOPICAL"},{"id":"51523-378","name":"octinoxate, titanium oxide and zind oxide cream","form":"CREAM","route":"TOPICAL"},{"id":"43419-509","name":"octinoxate, titanium dioxide, and zinc oxide","form":"LOTION","route":"TOPICAL"},{"id":"51346-332","name":"titanium dioxide, octinoxate, zinc oxide","form":"POWDER","route":"TOPICAL"},{"id":"51523-457","name":"octinoxate, titanium dioxide and zinc oxide cream","form":"CREAM","route":"TOPICAL"},{"id":"68828-079","name":"titanium dioxide, octinoxate\/ethylhexylmehtoxycinnamate","form":"LOTION","route":"TOPICAL"},{"id":"69039-206","name":"homosalate, octinoxate, octocrylene, titanium dioxide, zinc oxide","form":"STICK","route":"TOPICAL"},{"id":"10812-167","name":"octinoxate, octisalate, and titanium dioxide","form":"LOTION","route":"TOPICAL"},{"id":"58411-292","name":"octinoxate, octocrylene, and titanium dioxide","form":"CREAM","route":"TOPICAL"},{"id":"49967-361","name":"homosalate, octisalate, octocrylene and titanium dioxide","form":"CREAM","route":"TOPICAL"},{"id":"70227-001","name":"octinoxate, octocrylene, oxybenzone,titanium dioxide, zinc oxide","form":"STICK","route":"TOPICAL"},{"id":"0378-2250","name":"mycophenolate mofetil","form":"CAPSULE","route":"ORAL"},{"id":"70518-0442","name":"buprenorphine hydrochloride","form":"TABLET","route":"SUBLINGUAL"},{"id":"65162-415","name":"buprenorphine and naloxone","form":"TABLET","route":"SUBLINGUAL"},{"id":"53217-138","name":"buprenorphine hydrochloride and naloxone hydrochloride","form":"TABLET","route":"SUBLINGUAL"},{"id":"59011-751","name":"buprenorphine","form":"PATCH, EXTENDED RELEASE","route":"TRANSDERMAL"},{"id":"0054-0176","name":"buprenorphine hcl","form":"TABLET","route":"SUBLINGUAL"},{"id":"35356-004","name":"buprenorphine hydrochloride, naloxone hydrochloride","form":"TABLET","route":"SUBLINGUAL"},{"id":"0054-0188","name":"buprenorphine hydrochloride and naloxone hydrochloride dihydrate","form":"TABLET","route":"SUBLINGUAL"},{"id":"67046-997","name":"buprenorphine hydrochloride sublingual","form":"TABLET","route":"SUBLINGUAL"},{"id":"0069-0550","name":"sunitinib malate","form":"CAPSULE","route":"ORAL"}]